CHANGES.md
LICENSE.md
MANIFEST.in
README.md
VERSION
requirements-dev.txt
setup.py
sbg/__init__.py
sbg/cwl/__init__.py
sbg/cwl/consts.py
sbg/cwl/resources/expression_lib.js
sbg/cwl/resources/bash/util.sh
sbg/cwl/sbg/__init__.py
sbg/cwl/sbg/session.py
sbg/cwl/sbg/hints/__init__.py
sbg/cwl/sbg/hints/aws.py
sbg/cwl/sbg/hints/fs.py
sbg/cwl/sbg/hints/hint.py
sbg/cwl/sbg/hints/logs.py
sbg/cwl/sbg/hints/parallel.py
sbg/cwl/serialize/__init__.py
sbg/cwl/serialize/consts.py
sbg/cwl/serialize/context.py
sbg/cwl/serialize/deploy.py
sbg/cwl/serialize/inspector.py
sbg/cwl/serialize/plugins/__init__.py
sbg/cwl/serialize/plugins/base.py
sbg/cwl/serialize/plugins/toolz.py
sbg/cwl/tests/__init__.py
sbg/cwl/tests/v1_0/__init__.py
sbg/cwl/tests/v1_0/test_app.py
sbg/cwl/tests/v1_0/test_context.py
sbg/cwl/tests/v1_0/test_load.py
sbg/cwl/tests/v1_0/test_types.py
sbg/cwl/tests/v1_0/cmd/__init__.py
sbg/cwl/tests/v1_0/cmd/test_tool.py
sbg/cwl/tests/v1_0/sbg/__init__.py
sbg/cwl/tests/v1_0/sbg/test_session.py
sbg/cwl/tests/v1_0/wf/__init__.py
sbg/cwl/tests/v1_0/wf/test_workflow.py
sbg/cwl/v1_0/__init__.py
sbg/cwl/v1_0/app.py
sbg/cwl/v1_0/base.py
sbg/cwl/v1_0/check.py
sbg/cwl/v1_0/context.py
sbg/cwl/v1_0/hints.py
sbg/cwl/v1_0/load.py
sbg/cwl/v1_0/schema.py
sbg/cwl/v1_0/types.py
sbg/cwl/v1_0/util.py
sbg/cwl/v1_0/cmd/__init__.py
sbg/cwl/v1_0/cmd/input.py
sbg/cwl/v1_0/cmd/output.py
sbg/cwl/v1_0/cmd/tool.py
sbg/cwl/v1_0/requirement/__init__.py
sbg/cwl/v1_0/requirement/docker.py
sbg/cwl/v1_0/requirement/inline_javascript.py
sbg/cwl/v1_0/requirement/resource.py
sbg/cwl/v1_0/requirement/shell_command.py
sbg/cwl/v1_0/requirement/env/__init__.py
sbg/cwl/v1_0/requirement/env/env_def.py
sbg/cwl/v1_0/requirement/env/env_var.py
sbg/cwl/v1_0/requirement/schema_def/__init__.py
sbg/cwl/v1_0/requirement/schema_def/schema_def.py
sbg/cwl/v1_0/requirement/software/__init__.py
sbg/cwl/v1_0/requirement/software/software.py
sbg/cwl/v1_0/requirement/software/software_package.py
sevenbridges_cwl.egg-info/PKG-INFO
sevenbridges_cwl.egg-info/SOURCES.txt
sevenbridges_cwl.egg-info/dependency_links.txt
sevenbridges_cwl.egg-info/requires.txt
sevenbridges_cwl.egg-info/top_level.txt