Metadata-Version: 2.1
Name: sevenbridges-cwl
Version: 1.1.4
Summary: SBG Python library to create CWL tools and workflows
Home-page: UNKNOWN
Author: Seven Bridges Genomics Inc.
Author-email: filip.tubic@sbgenomics.com
Maintainer: Seven Bridges Genomics Inc.
Maintainer-email: filip.tubic@sbgenomics.com
License: Copyright (c) 2021 Seven Bridges Genomics
Keywords: seven bridges cwl common workflow language
Platform: POSIX
Platform: MacOS
Platform: Windows
Classifier: Intended Audience :: Developers
Classifier: License :: Other/Proprietary License
Classifier: Natural Language :: English
Classifier: Operating System :: POSIX
Classifier: Programming Language :: Python :: 3
